README
setup.py
timetra/__init__.py
timetra.pim.egg-info/PKG-INFO
timetra.pim.egg-info/SOURCES.txt
timetra.pim.egg-info/dependency_links.txt
timetra.pim.egg-info/entry_points.txt
timetra.pim.egg-info/not-zip-safe
timetra.pim.egg-info/requires.txt
timetra.pim.egg-info/top_level.txt
timetra/pim/__init__.py
timetra/pim/app.py
timetra/pim/caching.py
timetra/pim/compat.py
timetra/pim/finder.py
timetra/pim/formatting.py
timetra/pim/loading.py
timetra/pim/models.py
timetra/pim/processing.py
timetra/pim/reports.py
timetra/pim/settings.py
timetra/pim/stats.py
timetra/pim/xp_curses.py
timetra/pim/utils/__init__.py
timetra/pim/utils/formatdelta.py
timetra/pim/web/__init__.py
timetra/pim/web/flare/__init__.py
timetra/pim/web/flow/__init__.py
timetra/pim/web/providers/__init__.py
timetra/pim/web/providers/rstfiles.py
timetra/pim/web/providers/ttlbooks.py
timetra/pim/web/providers/yamlfiles.py
timetra/pim/web/providers/base/__init__.py