Metadata-Version: 1.1
Name: timetra.pim
Version: 0.0.1
Summary: Personal Information Manager with CLI + YAML
Home-page: https://github.com/neithere/timetra.pim
Author: Andrey Mikhaylenko
Author-email: neithere@gmail.com
License: GNU Lesser General Public License (LGPL), Version 3
Download-URL: https://github.com/neithere/timetra.pim/archive/master.zip
Keywords: cli command line diary pim personal information task manager
Platform: UNKNOWN
Classifier: Development Status :: 3 - Alpha
Classifier: Environment :: Console
Classifier: Intended Audience :: Developers
Classifier: Intended Audience :: End Users/Desktop
Classifier: License :: OSI Approved :: GNU Library or Lesser General Public License (LGPL)
Classifier: Programming Language :: Python
Classifier: Programming Language :: Python :: 2
Classifier: Programming Language :: Python :: 2.7
Classifier: Programming Language :: Python :: 3
Classifier: Programming Language :: Python :: 3.2
Classifier: Programming Language :: Python :: 3.3
Classifier: Topic :: Utilities
Classifier: Topic :: Software Development :: Libraries :: Python Modules
